crt/__init__.py
crt/cli.py
crt/option.py
crt/templates.py
crt/tools.py
crt/data/file_code.json
crt/data/templates.json
crtfiles-1.1.7.dist-info/LICENSE
crtfiles-1.1.7.dist-info/METADATA
crtfiles-1.1.7.dist-info/WHEEL
crtfiles-1.1.7.dist-info/entry_points.txt
crtfiles-1.1.7.dist-info/top_level.txt
crtfiles-1.1.7.dist-info/RECORD
