Metadata-Version: 2.1
Name: crtfiles
Version: 1.1.7
Summary: create files quickly and conveniently with the 'crt' utility
Home-page: https://github.com/feed619/crtfiles
Author: feed619
Author-email: azimovpro@gmail.com
License: MIT
Classifier: Programming Language :: Python :: 3.7
Classifier: License :: OSI Approved :: MIT License
Requires-Python: >=3.7
License-File: LICENSE
Requires-Dist: click
